cyeva/__init__.py
cyeva/errors.py
cyeva/config/directions/__init__.py
cyeva/config/levels/__init__.py
cyeva/config/levels/precip/__init__.py
cyeva/config/levels/wind/__init__.py
cyeva/core/__init__.py
cyeva/core/base.py
cyeva/core/binarize.py
cyeva/core/precip.py
cyeva/core/statistic.py
cyeva/core/temp.py
cyeva/core/weather_code.py
cyeva/core/wind.py
cyeva/utils/__init__.py
cyeva-0.2.2.dist-info/METADATA
cyeva-0.2.2.dist-info/WHEEL
cyeva-0.2.2.dist-info/licenses/LICENSE
cyeva-0.2.2.dist-info/RECORD
