Metadata-Version: 2.3
Name: cyeva
Version: 0.2.2
Summary: A package to evaluate weather forecast correction
Project-URL: Documentation, https://caiyunapp.github.io/cyeva
Project-URL: Issues, https://github.com/caiyunapp/cyeva/issues
Project-URL: Source Code, https://github.com/caiyunapp/cyeva
Maintainer-email: caiyunapp <oss@caiyunapp.com>, ringsaturn <ringsaturn.me@gmail.com>
License:                                  Apache License
License-File: LICENSE
Keywords: atmospheric-science,mathmatics
Classifier: Development Status :: 4 - Beta
Classifier: Framework :: Sphinx
Classifier: Operating System :: MacOS
Classifier: Operating System :: Microsoft :: Windows
Classifier: Operating System :: POSIX :: Linux
Classifier: Programming Language :: Python :: 3.10
Classifier: Programming Language :: Python :: 3.11
Classifier: Programming Language :: Python :: 3.12
Classifier: Topic :: Scientific/Engineering :: Atmospheric Science
Classifier: Topic :: Scientific/Engineering :: Mathematics
Requires-Python: <3.13,>=3.10
Requires-Dist: numpy>=2.1.2
Requires-Dist: pandas>=2.2.3
Requires-Dist: pint>=0.24.3
Requires-Dist: scipy>=1.14.1
